fastapi_structlog/__init__.py
fastapi_structlog/base.py
fastapi_structlog/custom_processors.py
fastapi_structlog/exceptions.py
fastapi_structlog/factory.py
fastapi_structlog/log.py
fastapi_structlog/py.typed
fastapi_structlog/settings.py
fastapi_structlog/types_.py
fastapi_structlog/utils.py
fastapi_structlog/db_handler/__init__.py
fastapi_structlog/db_handler/handler.py
fastapi_structlog/db_handler/model.py
fastapi_structlog/middleware/__init__.py
fastapi_structlog/middleware/access_log.py
fastapi_structlog/middleware/context_scope.py
fastapi_structlog/middleware/current_scope.py
fastapi_structlog/middleware/structlog.py
fastapi_structlog/middleware/utils.py
fastapi_structlog/sentry/__init__.py
fastapi_structlog/sentry/initialization.py
fastapi_structlog/sentry/settings.py
fastapi_structlog-0.7.1.dist-info/METADATA
fastapi_structlog-0.7.1.dist-info/WHEEL
fastapi_structlog-0.7.1.dist-info/licenses/LICENSE
fastapi_structlog-0.7.1.dist-info/RECORD
