Metadata-Version: 2.4
Name: fastapi-structlog
Version: 0.7.1
Summary: Structured logs and middleware for fastapi with sentry integration
Project-URL: homepage, https://github.com/redb0/fastapi-logger
Project-URL: repository, https://github.com/redb0/fastapi-logger
Author-email: Vladimir Voronov <voronov.volodya2013@yandex.ru>
License: MIT
License-File: LICENSE
Keywords: fastapi,logging,structlog
Classifier: Framework :: FastAPI
Classifier: License :: OSI Approved :: MIT License
Classifier: Programming Language :: Python
Classifier: Programming Language :: Python :: 3
Classifier: Programming Language :: Python :: 3.9
Classifier: Programming Language :: Python :: 3.10
Classifier: Programming Language :: Python :: 3.11
Classifier: Programming Language :: Python :: 3.12
Classifier: Programming Language :: Python :: 3.13
Classifier: Programming Language :: Python :: 3.14
Classifier: Topic :: Internet
Classifier: Topic :: Software Development
Classifier: Topic :: Software Development :: Libraries
Classifier: Topic :: Software Development :: Libraries :: Python Modules
Classifier: Topic :: System :: Logging
Requires-Python: <4.0.0,>=3.9
Requires-Dist: asgi-correlation-id<5.0.0,>=4.3.4
Requires-Dist: orjson<4.0.0,>=3.11.5
Requires-Dist: pydantic-settings<3.0.0,>=2.7.1
Requires-Dist: pydantic<3.0.0,>=2.12.5
Requires-Dist: rich<14.0.0,>=13.9.4
Requires-Dist: sentry-sdk<3.0.0,>=2.21.0
Requires-Dist: sqlmodel<0.1.0,>=0.0.31
Requires-Dist: structlog-sentry<3.0.0,>=2.2.1
Requires-Dist: structlog<26.0.0,>=25.1.0
